chess_mcp/__init__.py
chess_mcp/__main__.py
chess_mcp-0.1.7.dist-info/METADATA
chess_mcp-0.1.7.dist-info/WHEEL
chess_mcp-0.1.7.dist-info/RECORD
