Metadata-Version: 2.4
Name: chess-mcp
Version: 0.1.7
Summary: A Model Context Protocol server for chess games using Stockfish
Project-URL: Homepage, https://github.com/yourusername/chess-mcp
Project-URL: Repository, https://github.com/yourusername/chess-mcp
Project-URL: Issues, https://github.com/yourusername/chess-mcp/issues
Author-email: Your Name <your.email@example.com>
License-Expression: MIT
Classifier: Development Status :: 3 - Alpha
Classifier: Intended Audience :: Developers
Classifier: License :: OSI Approved :: MIT License
Classifier: Programming Language :: Python :: 3
Classifier: Programming Language :: Python :: 3.13
Classifier: Topic :: Games/Entertainment :: Board Games
Requires-Python: >=3.13
Requires-Dist: mcp[cli]>=1.24.0
Requires-Dist: python-chess>=1.999
